metaflow_extensions/outerbounds/__init__.py
metaflow_extensions/outerbounds/remote_config.py
metaflow_extensions/outerbounds/config/__init__.py
metaflow_extensions/outerbounds/plugins/__init__.py
metaflow_extensions/outerbounds/plugins/auth_server.py
metaflow_extensions/outerbounds/plugins/perimeters.py
metaflow_extensions/outerbounds/plugins/apps/__init__.py
metaflow_extensions/outerbounds/plugins/apps/app_cli.py
metaflow_extensions/outerbounds/plugins/apps/app_deploy_decorator.py
metaflow_extensions/outerbounds/plugins/apps/app_utils.py
metaflow_extensions/outerbounds/plugins/apps/consts.py
metaflow_extensions/outerbounds/plugins/apps/deploy_decorator.py
metaflow_extensions/outerbounds/plugins/apps/supervisord_utils.py
metaflow_extensions/outerbounds/plugins/apps/core/__init__.py
metaflow_extensions/outerbounds/plugins/apps/core/_state_machine.py
metaflow_extensions/outerbounds/plugins/apps/core/app_config.py
metaflow_extensions/outerbounds/plugins/apps/core/artifacts.py
metaflow_extensions/outerbounds/plugins/apps/core/capsule.py
metaflow_extensions/outerbounds/plugins/apps/core/click_importer.py
metaflow_extensions/outerbounds/plugins/apps/core/config_schema.yaml
metaflow_extensions/outerbounds/plugins/apps/core/dependencies.py
metaflow_extensions/outerbounds/plugins/apps/core/deployer.py
metaflow_extensions/outerbounds/plugins/apps/core/perimeters.py
metaflow_extensions/outerbounds/plugins/apps/core/secrets.py
metaflow_extensions/outerbounds/plugins/apps/core/utils.py
metaflow_extensions/outerbounds/plugins/apps/core/validations.py
metaflow_extensions/outerbounds/plugins/apps/core/_vendor/__init__.py
metaflow_extensions/outerbounds/plugins/apps/core/_vendor/spinner/__init__.py
metaflow_extensions/outerbounds/plugins/apps/core/_vendor/spinner/spinners.py
metaflow_extensions/outerbounds/plugins/apps/core/code_package/__init__.py
metaflow_extensions/outerbounds/plugins/apps/core/code_package/code_packager.py
ob_metaflow_extensions-1.5.0.dist-info/METADATA
ob_metaflow_extensions-1.5.0.dist-info/WHEEL
ob_metaflow_extensions-1.5.0.dist-info/top_level.txt
ob_metaflow_extensions-1.5.0.dist-info/RECORD
